spright/__init__.py
spright/analytical_model.py
spright/core.py
spright/distribution.py
spright/io.py
spright/lerp.py
spright/lnlikelihood.py
spright/lpf.py
spright/mock.py
spright/model.py
spright/rdmodel.py
spright/relationmap.py
spright/rmestimator.py
spright/rmrelation.py
spright/util.py
spright/version.py
spright/data/TEPCat.csv
spright/data/exoeu_fgk_a21.fits
spright/data/exoeu_fgk_z19.fits
spright/data/exoeu_m_a21.fits
spright/data/exoeu_m_z19.fits
spright/data/exoplanet_eu.csv
spright/data/rocky_zeng19.fits
spright/data/stpm.fits
spright/data/stpm_230202.csv
spright/data/stpm_a21.fits
spright/data/tepcat_fgk_a21.fits
spright/data/tepcat_fgk_z19.fits
spright/data/tepcat_m_a21.fits
spright/data/tepcat_m_z19.fits
spright/data/water_aguichine21.fits
spright/data/water_zeng19.fits
spright/scripts/__init__.py
spright/scripts/spright.py
spright-25.6.3.dist-info/licenses/LICENSE
spright-25.6.3.dist-info/METADATA
spright-25.6.3.dist-info/WHEEL
spright-25.6.3.dist-info/entry_points.txt
spright-25.6.3.dist-info/top_level.txt
spright-25.6.3.dist-info/RECORD
